README.txt
setup.cfg
setup.py
docs/HISTORY.txt
docs/LICENSE.GPL
docs/LICENSE.txt
docs/MANUAL.txt
raptus/__init__.py
raptus.article.contentfader.egg-info/PKG-INFO
raptus.article.contentfader.egg-info/SOURCES.txt
raptus.article.contentfader.egg-info/dependency_links.txt
raptus.article.contentfader.egg-info/entry_points.txt
raptus.article.contentfader.egg-info/namespace_packages.txt
raptus.article.contentfader.egg-info/not-zip-safe
raptus.article.contentfader.egg-info/requires.txt
raptus.article.contentfader.egg-info/top_level.txt
raptus/article/__init__.py
raptus/article/contentfader/__init__.py
raptus/article/contentfader/configure.zcml
raptus/article/contentfader/browser/__init__.py
raptus/article/contentfader/browser/configure.zcml
raptus/article/contentfader/browser/contentfader.gif
raptus/article/contentfader/browser/contentfader.init.js
raptus/article/contentfader/browser/contentfader.pt
raptus/article/contentfader/browser/contentfader.py
raptus/article/contentfader/browser/contentfader_teaser.gif
raptus/article/contentfader/i18n/raptus.article-de.po
raptus/article/contentfader/i18n/raptus.article-fr.po
raptus/article/contentfader/i18n/raptus.article.pot
raptus/article/contentfader/profiles/default/cssregistry.xml
raptus/article/contentfader/profiles/default/jsregistry.xml
raptus/article/contentfader/profiles/default/metadata.xml
raptus/article/contentfader/profiles/default/propertiestool.xml
raptus/article/contentfader/profiles/default/skins.xml
raptus/article/contentfader/profiles/default/viewlets.xml
raptus/article/contentfader/skins/raptus_article_contentfader/raptus.article.contentfader.css.dtml